jako/__init__.py
jako/database/__init__.py
jako/database/database.py
jako/distribute/DistributedScan.py
jako/distribute/RemoteScan.py
jako/distribute/__init__.py
jako/distribute/distribute_database.py
jako/distribute/distribute_finish.py
jako/distribute/distribute_params.py
jako/distribute/distribute_run.py
jako/distribute/distribute_utils.py
jako/distribute/script_string.py
jako-0.1.1.dist-info/LICENSE
jako-0.1.1.dist-info/METADATA
jako-0.1.1.dist-info/WHEEL
jako-0.1.1.dist-info/top_level.txt
jako-0.1.1.dist-info/RECORD
