Metadata-Version: 2.1
Name: jako
Version: 0.1.1
Summary: Distributed Hyperparameter Experiments with Talos
Home-page: http://autonom.io
Author: Mikko Kotila
Author-email: mailme@mikkokotila.com
Maintainer: Mikko Kotila
Maintainer-email: mailme@mikkokotila.com
License: MIT
Download-URL: https://github.com/autonomio/jako/
Platform: UNKNOWN
Classifier: Intended Audience :: Science/Research
Classifier: Programming Language :: Python :: 3.7
Classifier: Programming Language :: Python :: 3.8
Classifier: Programming Language :: Python :: 3.9
Classifier: License :: OSI Approved :: MIT License
Classifier: Topic :: Scientific/Engineering :: Human Machine Interfaces
Classifier: Topic :: Scientific/Engineering :: Artificial Intelligence
Classifier: Topic :: Scientific/Engineering :: Mathematics
Classifier: Operating System :: POSIX
Classifier: Operating System :: Unix
Classifier: Operating System :: MacOS
Classifier: Operating System :: Microsoft :: Windows :: Windows 10
License-File: LICENSE
Requires-Dist: talos
Requires-Dist: numpy
Requires-Dist: pandas
Requires-Dist: paramiko
Requires-Dist: psycopg2-binary
Requires-Dist: sqlalchemy
Requires-Dist: sqlalchemy-utils
